gfwlist2pac/__init__.py
gfwlist2pac/main.py
gfwlist2pac/resources/__init__.py
gfwlist2pac/resources/abp.js
gfwlist2pac/resources/builtin.txt
gfwlist2pac/resources/proxy.pac
gfwlist2pac/resources/tld.txt
gfwlist2pac-1.1.4.dist-info/LICENSE
gfwlist2pac-1.1.4.dist-info/METADATA
gfwlist2pac-1.1.4.dist-info/WHEEL
gfwlist2pac-1.1.4.dist-info/entry_points.txt
gfwlist2pac-1.1.4.dist-info/top_level.txt
gfwlist2pac-1.1.4.dist-info/RECORD
