Metadata-Version: 2.1
Name: gfwlist2pac
Version: 1.1.4
Summary: convert gfwlist2pac to pac
Home-page: https://github.com/clowwindy/gfwlist2pac
Author: clowwindy
Author-email: clowwindy42@gmail.com
License: MIT
Platform: UNKNOWN
Classifier: License :: OSI Approved :: MIT License
Classifier: Programming Language :: Python :: 2
Classifier: Programming Language :: Python :: 2.6
Classifier: Programming Language :: Python :: 2.7
Classifier: Programming Language :: Python :: 3
Classifier: Programming Language :: Python :: 3.6
